{
  "loginInfo": {
    "success": {
      "success": true,
      "message": "",
      "code": 0,
      "content": {
        "userId": 1,
        "nickname": "管理员",
        "descr": "描述",
        "permissions": {
          "ebook": 1,
          "user": 2,
          "topic": 3
        }
      }
    },
    "failed": {
      "success": false,
      "message": "登录失败",
      "code": 0,
      "content": {}
    }
  },
  "login": {
    "success": {
      "success": true,
      "message": "登录成功",
      "code": 0,
      "content": {
        "userId": 1,
        "nickname": "管理员",
        "permissions": {
          "ebook": 1,
          "user": 2,
          "topic": 3
        }
      }
    }
  },
  "logout": {
    "success": {
      "success": true,
      "message": "",
      "code": 0,
      "content": {}
    }
  }
}